{
  "project_info": {
    "project_number": "627962654539",
    "project_id": "thumbhero-ee3ca",
    "storage_bucket": "thumbhero-ee3ca.appspot.com"
  },
  "client": [
    {
      "client_info": {
        "mobilesdk_app_id": "1:627962654539:android:ece07b7608916a4e32c2ce",
        "android_client_info": {
          "package_name": "thumb.hero"
        }
      },
      "oauth_client": [
        {
          "client_id": "627962654539-qi91573bvtveh65sqtntst00vev5su80.apps.googleusercontent.com",
          "client_type": 1,
          "android_info": {
            "package_name": "thumb.hero",
            "certificate_hash": "cac4f265d048b573b03a092c9d53aebce884f74f"
          }
        },
        {
          "client_id": "627962654539-9calrsbv7ajqjiv285hbm8k01ki39ki9.apps.googleusercontent.com",
          "client_type": 3
        }
      ],
      "api_key": [
        {
          "current_key": "AIzaSyAripwRA8li4U0Dko2v6IQ4n0i_p5prbfU"
        }
      ],
      "services": {
        "appinvite_service": {
          "other_platform_oauth_client": [
            {
              "client_id": "627962654539-9calrsbv7ajqjiv285hbm8k01ki39ki9.apps.googleusercontent.com",
              "client_type": 3
            }
          ]
        }
      }
    }
  ],
  "configuration_version": "1"
}